{
  "parent": "minecraft:recipes/root",
  "criteria": {
    "hasAirStone": {
      "conditions": {
        "items": [
          {
            "items": "gravelmon:air_stone"
          }
        ]
      },
      "trigger": "minecraft:inventory_changed"
    },
    "has_the_recipe": {
      "conditions": {
        "recipe": "gravelmon:air_stone_block"
      },
      "trigger": "minecraft:recipe_unlocked"
    }
  },
  "requirements": [
    [
      "has_the_recipe",
      "hasAirStone"
    ]
  ],
  "rewards": {
    "recipes": [
      "gravelmon:air_stone_block"
    ]
  }
}