{
  "name": "Bombull",
  "primaryType": "fire",
  "secondaryType": "steel",
  "catchRate": 45,
  "maleRatio": 0.75,
  "baseExperienceYield": 142,
  "experienceGroup": "medium_slow",
  "eggCycles": 50,
  "baseFriendship": 70,
  "preEvolution": "bullit",
  "baseScale": 0.5508196721311475,
  "cannotDynamax": false,
  "abilities": [
    "blaze",
    "h:heavymetal"
  ],
  "behaviour": {
    "resting": {
      "canSleep": true,
      "willSleepOnBed": false,
      "depth": "normal",
      "light": "0-6"
    },
    "moving": {
      "fly": {
        "canFly": false
      },
      "canLook": true,
      "walk": {
        "canWalk": true,
        "avoidsLand": false
      },
      "swim": {
        "swimSpeed": 0.1,
        "canSwimInWater": true,
        "canSwimInLava": false,
        "canBreatheUnderlava": false,
        "canBreatheUnderwater": false,
        "canWalkOnLava": false
      }
    }
  },
  "baseStats": {
    "hp": 80,
    "attack": 70,
    "defence": 95,
    "special_attack": 55,
    "special_defence": 75,
    "speed": 45
  },
  "evYield": {
    "hp": 0,
    "attack": 0,
    "defence": 2,
    "special_attack": 0,
    "special_defence": 0,
    "speed": 0
  },
  "eggGroups": [
    "field"
  ],
  "drops": {},
  "moves": [
    "1:ember",
    "1:metalclaw",
    "1:bulkup",
    "1:irondefense",
    "1:willowisp",
    "1:healbell",
    "1:growl",
    "1:screech",
    "1:calmmind",
    "1:bulkup",
    "1:healbell",
    "1:wish",
    "3:firespin",
    "3:irontail",
    "3:taunt",
    "3:calmmind",
    "3:wish",
    "6:flamecharge",
    "6:smartstrike",
    "6:substitute",
    "6:taunt",
    "9:flameburst",
    "9:mirrorshot",
    "9:rest",
    "9:substitute",
    "12:flamethrower",
    "12:flashcannon",
    "12:rest",
    "15:fireblast",
    "15:steelbeam",
    "18:ember",
    "18:metalclaw",
    "21:growl",
    "21:screech",
    "24:quickattack",
    "24:irontail",
    "27:flamecharge",
    "27:smartstrike",
    "30:firepunch",
    "30:ironhead",
    "33:willowisp",
    "33:meteormash",
    "36:flareblitz",
    "tm:terablast"
  ],
  "labels": [
    "theos",
    "not_modeled",
    "starter",
    "fakemon",
    "fakemonevolution"
  ],
  "pokedex": [
    "cobblemon.species.bombull.desc"
  ],
  "height": 14,
  "weight": 520,
  "aspects": [],
  "evolutions": [
    {
      "id": "bombull_brassear",
      "variant": "level_up",
      "result": "brassear",
      "consumeHeldItem": false,
      "learnableMoves": [],
      "requirements": [
        {
          "variant": "level",
          "minLevel": "36"
        }
      ],
      "permanent": true
    }
  ],
  "nationalPokedexNumber": 10333,
  "shoulderMountable": false,
  "hitbox": {
    "width": 3.8125,
    "height": 3.8125,
    "fixed": false
  },
  "features": [],
  "implemented": true,
  "forms": []
}