{
   "target": "cobblemon:sawsbuck",
   "forms": [{
  "name": "Epoch",
  "primaryType": "normal",
  "secondaryType": "fire",
  "abilities": [
    "flamebody",
    "quickfeet",
    "h:limber"
  ],
  "baseStats": {
    "hp": 70,
    "attack": 100,
    "defence": 65,
    "special_attack": 105,
    "special_defence": 50,
    "speed": 85
  },
  "behaviour": {
    "resting": {
        "canSleep": true,
        "willSleepOnBed": false,        "depth": "normal",
        "light": "0-6"
    },
    "moving": {
        "fly": {
            "canFly": false
        },
        "canLook": true,
        "walk": {
            "canWalk": true,
            "avoidsLand": false
        },
        "swim": {
            "swimSpeed": 0.1,
            "canSwimInWater": true,
            "canBreatheUnderwater": false
        }
    }
  },
  "catchRate": 100,
  "shoulderMountable": false,
  "baseExperienceYield": 166,
  "experienceGroup": "medium_fast",
  "eggCycles": 50,
  "eggGroups": [
    "field"
  ],
  "moves": [
    "56:flareblitz",
    "1:quickattack",
    "20:sunnyday",
    "4:leer",
    "13:charm",
    "13:captivate",
    "28:doublekick",
    "44:jumpkick",
    "10:flamecharge",
    "7:protect",
    "32:morningsun",
    "40:doubleedge",
    "16:hornattack",
    "60:highjumpkick",
    "1:firelash",
    "52:solarblade",
    "48:swordsdance",
    "tm:acrobatics",
    "tm:attract",
    "tm:bodyslam",
    "tm:bounce",
    "tm:bulldoze",
    "tm:burningjealousy",
    "tm:charm",
    "tm:earthpower",
    "tm:earthquake",
    "tm:energyball",
    "tm:falseswipe",
    "tm:flamethrower",
    "tm:flareblitz",
    "tm:heatwave",
    "tm:hiddenpower",
    "tm:highhorsepower",
    "tm:incinerate",
    "tm:mist",
    "tm:mysticalfire",
    "tm:playrough",
    "tm:protect",
    "tm:rest",
    "tm:return",
    "tm:safeguard",
    "tm:sleeptalk",
    "tm:solarbeam",
    "tm:substitute",
    "tm:sunnyday",
    "tm:swordsdance",
    "tm:synthesis",
    "tm:terrainpulse",
    "tm:toxic",
    "tm:triattack",
    "tm:voltswitch",
    "tm:weatherball",
    "tm:wildcharge",
    "tm:willowisp",
    "tm:workup",
    "tm:zenheadbutt"  ],
  "labels": [
    "soulstones",
    "not_modeled"
  ],
  "pokedex": [
    "cobblemon.species.epochsawsbuck.desc"
  ],
  "baseScale": 0.31666666666666665,
  "hitbox": {
    "width": 6.0,
    "height": 6.0,
    "fixed": false
  },
  "baseFriendship": 70,
  "evYield": {
    "hp": 0,
    "attack": 1,
    "defence": 0,
    "special_attack": 0,
    "special_defence": 0,
    "speed": 0
  },
  "height": 19,
  "weight": 925,
  "aspects": ["epoch"],
  "cannotDynamax": false
}
], "features": [
"epoch"
  ]
}