{
  "enabled": true,
  "neededInstalledMods": [],
  "neededUninstalledMods": [],
  "spawns": [
    {
      "id": "cereblast-01",
      "pokemon": "cereblast",
      "presets": [
        "natural"
      ],
      "type": "pokemon",
      "context": "grounded",
      "bucket": "ultra-rare",
      "level": "51-65",
      "weight": 0.4,
      "condition": {
        "biomes": [
          "#cobblemon:is_sky",
          "#cobblemon:is_mountain"
        ],
        "timeRange": "night",
        "minSkyLight": 8,
        "maxSkyLight": 15
      }
    }
  ]
}