{
  "enabled": true,
  "neededInstalledMods": [],
  "neededUninstalledMods": [],
  "spawns": [
    {
      "id": "debumue-01",
      "pokemon": "debumue",
      "presets": [
        "natural",
        "wild"
      ],
      "type": "pokemon",
      "context": "grounded",
      "bucket": "uncommon",
      "level": "5-25",
      "weight": 9.0,
      "condition": {
        "biomes": [
          "#cobblemon:is_desert"
        ],
        "timeRange": "night",
        "minSkyLight": 8,
        "maxSkyLight": 15
      },
      "weightMultiplier": {
        "multiplier": 5.0,
        "condition": {
          "neededNearbyBlocks": [
            "minecraft:packed_mud"
          ]
        }
      }
    }
  ]
}