{
  "enabled": true,
  "neededInstalledMods": [],
  "neededUninstalledMods": [],
  "spawns": [
    {
      "id": "humwing-01",
      "pokemon": "humwing",
      "presets": [
        "natural"
      ],
      "type": "pokemon",
      "context": "grounded",
      "bucket": "uncommon",
      "level": "13-34",
      "weight": 6.0,
      "condition": {
        "biomes": [
          "#cobblemon:is_jungle",
          "#cobblemon:is_floral"
        ],
        "minSkyLight": 8,
        "maxSkyLight": 15
      },
      "weightMultiplier": {
        "multiplier": 5.0,
        "condition": {
          "neededNearbyBlocks": [
            "minecraft:pink_stained_glass"
          ]
        }
      }
    }
  ]
}