{
  "enabled": true,
  "neededInstalledMods": [],
  "neededUninstalledMods": [],
  "spawns": [
    {
      "id": "mieltzar-01",
      "pokemon": "mieltzar",
      "presets": [
        "honey_tree"
      ],
      "type": "pokemon",
      "context": "grounded",
      "bucket": "common",
      "level": "25-43",
      "weight": 0.30000000000000004,
      "condition": {
        "biomes": [
          "#gravelmon:is_deciduous_forest",
          "#cobblemon:is_plains"
        ]
      },
      "weightMultiplier": {
        "multiplier": 5.0,
        "condition": {
          "neededNearbyBlocks": [
            "minecraft:honeycomb_block"
          ]
        }
      }
    }
  ]
}