{
  "enabled": true,
  "neededInstalledMods": [],
  "neededUninstalledMods": [],
  "spawns": [
    {
      "id": "ogopoing-01",
      "pokemon": "ogopoing",
      "presets": [
        "natural"
      ],
      "type": "pokemon",
      "context": "grounded",
      "bucket": "uncommon",
      "level": "3-22",
      "weight": 4.0,
      "condition": {
        "biomes": [
          "#cobblemon:is_cave"
        ],
        "minSkyLight": 0,
        "maxSkyLight": 7
      },
      "weightMultiplier": {
        "multiplier": 5.0,
        "condition": {
          "neededNearbyBlocks": [
            "minecraft:raw_gold_block"
          ]
        }
      }
    }
  ]
}