{
  "enabled": true,
  "neededInstalledMods": [],
  "neededUninstalledMods": [],
  "spawns": [
    {
      "id": "vanillurgy-01",
      "pokemon": "vanillurgy",
      "presets": [
        "natural",
        "wild"
      ],
      "type": "pokemon",
      "context": "grounded",
      "bucket": "uncommon",
      "level": "47-67",
      "weight": 0.05,
      "condition": {
        "biomes": [
          "#cobblemon:is_snowy_forest"
        ],
        "minSkyLight": 8,
        "maxSkyLight": 15,
        "timeRange": "night"
      },
      "weightMultiplier": {
        "multiplier": 5.0,
        "condition": {
          "neededNearbyBlocks": [
            "minecraft:packed_ice"
          ]
        }
      }
    }
  ]
}