{
  "implemented": true,
  "name": "Aviterate",
  "nationalPokedexNumber": 3077,
  "primaryType": "fire",
  "secondaryType": "electric",
  "abilities": [
    "blaze"  ],
  "baseStats": {
    "hp": 80,
    "attack": 90,
    "defence": 75,
    "special_attack": 90,
    "special_defence": 75,
    "speed": 120
  },
  "behaviour": {
    "resting": {
        "canSleep": true,
        "willSleepOnBed": false,        "depth": "normal",
        "light": "0-6"
    },
    "moving": {
        "fly": {
            "canFly": false
        },
        "canLook": true,
        "walk": {
            "canWalk": true,
            "avoidsLand": false
        },
        "swim": {
            "swimSpeed": 0.1,
            "canSwimInWater": true,
            "canBreatheUnderwater": false
        }
    }
  },
  "catchRate": 45,
  "maleRatio": 0.5,
  "shoulderMountable": false,
  "baseExperienceYield": 231,
  "experienceGroup": "medium_slow",
  "eggCycles": 50,
  "eggGroups": [
    "flying"
  ],
  "moves": [
    "1:ember",
    "1:tackle",
    "4:taunt",
    "8:bite",
    "12:incinerate",
    "16:thundershock",
    "20:firefang",
    "24:headbutt",
    "28:firepunch",
    "32:uproar",
    "36:thunderbolt",
    "40:flareblitz",
    "44:thrash",
    "48:thunder"  ],
  "labels": [
    "hiza",
    "not_modeled",
    "fakemon",
    "fakemonevolution"
  ],
  "pokedex": [
    "cobblemon.species.aviterate.desc"
  ],
  "preEvolution": "pyrebolt",
  "baseScale": 0.31666666666666665,
  "hitbox": {
    "width": 6.0,
    "height": 6.0,
    "fixed": false
  },
  "baseFriendship": 70,
  "evYield": {
    "hp": 0,
    "attack": 0,
    "defence": 0,
    "special_attack": 0,
    "special_defence": 0,
    "speed": 3
  },
  "height": 19,
  "weight": 165,
  "aspects": [],
"features": [

  ],  "cannotDynamax": false
}