{
  "name": "Jestrick",
  "primaryType": "fairy",
  "secondaryType": "ghost",
  "catchRate": 60,
  "maleRatio": 0.5,
  "baseExperienceYield": 60,
  "experienceGroup": "erratic",
  "eggCycles": 50,
  "baseFriendship": 70,
  "preEvolution": "jestreat",
  "baseScale": 0.2958904109589041,
  "cannotDynamax": false,
  "abilities": [
    "prankster",
    "h:cursedbody"
  ],
  "behaviour": {
    "resting": {
      "canSleep": true,
      "willSleepOnBed": false,
      "depth": "normal",
      "light": "0-6"
    },
    "moving": {
      "fly": {
        "canFly": false
      },
      "canLook": true,
      "walk": {
        "canWalk": true,
        "avoidsLand": false
      },
      "swim": {
        "swimSpeed": 0.1,
        "canSwimInWater": true,
        "canSwimInLava": false,
        "canBreatheUnderlava": false,
        "canBreatheUnderwater": false,
        "canWalkOnLava": false
      }
    }
  },
  "baseStats": {
    "hp": 65,
    "attack": 80,
    "defence": 60,
    "special_attack": 80,
    "special_defence": 110,
    "speed": 100
  },
  "evYield": {
    "hp": 0,
    "attack": 0,
    "defence": 0,
    "special_attack": 0,
    "special_defence": 0,
    "speed": 0
  },
  "eggGroups": [
    "field"
  ],
  "drops": {},
  "moves": [
    "1:copycat",
    "1:scratch",
    "1:splash",
    "1:woodhammer",
    "6:shadowsneak",
    "12:doubleteam",
    "18:babydolleyes",
    "24:mimic",
    "30:honeclaws",
    "36:slash",
    "42:shadowclaw",
    "48:charm",
    "54:playrough",
    "60:painsplit",
    "tm:terablast"
  ],
  "labels": [
    "hiza",
    "not_modeled",
    "fakemon",
    "fakemonevolution"
  ],
  "pokedex": [
    "cobblemon.species.jestrick.desc"
  ],
  "height": 9,
  "weight": 165,
  "aspects": [],
  "evolutions": [],
  "nationalPokedexNumber": 2977,
  "shoulderMountable": false,
  "hitbox": {
    "width": 4.5625,
    "height": 4.5625,
    "fixed": false
  },
  "features": [],
  "implemented": true,
  "forms": []
}