{
  "implemented": true,
  "name": "primmoiselle",
  "nationalPokedexNumber": 3568,
  "primaryType": "normal",
  "secondaryType": "flying",
  "abilities": [
    "queenlymajesty",
    "h:queenlymajesty"
  ],
  "baseStats": {
    "hp": 110,
    "attack": 55,
    "defence": 55,
    "special_attack": 115,
    "special_defence": 115,
    "speed": 80
  },
  "behaviour": {
    "resting": {
        "canSleep": true,
        "willSleepOnBed": false,        "depth": "normal",
        "light": "0-6"
    },
    "moving": {
        "fly": {
            "canFly": false
        },
        "canLook": true,
        "walk": {
            "canWalk": true,
            "avoidsLand": false
        },
        "swim": {
            "swimSpeed": 0.1,
            "canSwimInWater": true,
            "canBreatheUnderwater": false
        }
    }
  },
  "catchRate": 45,
  "maleRatio": 0.0,
  "shoulderMountable": false,
  "baseExperienceYield": 239,
  "experienceGroup": "medium_fast",
  "eggCycles": 50,
  "eggGroups": [
    "fairy"
  ],
  "moves": [
    "1:doubleslap",
    "5:disarmingvoicesound",
    "8:gust",
    "11:helpinghand",
    "15:roundsound",
    "19:heartstamp",
    "25:followme",
    "29:airslash",
    "34:defog",
    "39:hypervoicesound",
    "43:tailwind",
    "48:mimic",
    "52:afteryou",
    "57:hurricane",
    "tm:bounce",
    "tm:tailwind",
    "tm:afteryou",
    "tm:snoresound",
    "tm:chargebeam",
    "tm:shadowball",
    "tm:flamethrower",
    "tm:sunnyday",
    "tm:acrobatics",
    "tm:aerialace",
    "tm:defog",
    "tm:fly",
    "tm:skydrop",
    "tm:icebeam",
    "tm:attract",
    "tm:confide",
    "tm:echoedvoicesound",
    "tm:facade",
    "tm:frustration",
    "tm:gigaimpact",
    "tm:hiddenpower",
    "tm:hyperbeam",
    "tm:protect",
    "tm:psychup",
    "tm:return",
    "tm:roundsound",
    "tm:safeguard",
    "tm:sleeptalksound",
    "tm:substitute",
    "tm:swagger",
    "tm:toxic",
    "tm:calmmind",
    "tm:lightscreen",
    "tm:reflect",
    "tm:rest",
    "tm:raindance"  ],
  "labels": [
    "nosto",
    "not_modeled",
    "fakemon",
    "fakemonevolution"
  ],
  "pokedex": [
    "cobblemon.species.primmoiselle.desc"
  ],
  "preEvolution": "primmadame",
  "baseScale": 0.625,
  "hitbox": {
    "width": 6.0,
    "height": 6.0,
    "fixed": false
  },
  "baseFriendship": 70,
  "evYield": {
    "hp": 0,
    "attack": 0,
    "defence": 0,
    "special_attack": 1,
    "special_defence": 2,
    "speed": 0
  },
  "height": 25,
  "weight": 165,
  "aspects": [],
"features": [

  ],  "cannotDynamax": false
}