{
  "name": "Magemeltre",
  "primaryType": "fire",
  "secondaryType": "psychic",
  "catchRate": 3,
  "maleRatio": 0.0,
  "baseExperienceYield": 285,
  "experienceGroup": "slow",
  "eggCycles": 50,
  "baseFriendship": 70,
  "baseScale": 0.4,
  "cannotDynamax": false,
  "abilities": [
    "keeneye",
    "h:neuroforce"
  ],
  "behaviour": {
    "resting": {
      "canSleep": true,
      "willSleepOnBed": false,
      "depth": "normal",
      "light": "0-6"
    },
    "moving": {
      "fly": {
        "canFly": false
      },
      "canLook": true,
      "walk": {
        "canWalk": true,
        "avoidsLand": false
      },
      "swim": {
        "swimSpeed": 0.1,
        "canSwimInWater": true,
        "canSwimInLava": false,
        "canBreatheUnderlava": false,
        "canBreatheUnderwater": false,
        "canWalkOnLava": false
      }
    }
  },
  "baseStats": {
    "hp": 80,
    "attack": 85,
    "defence": 65,
    "special_attack": 135,
    "special_defence": 95,
    "speed": 110
  },
  "evYield": {
    "hp": 0,
    "attack": 0,
    "defence": 0,
    "special_attack": 3,
    "special_defence": 0,
    "speed": 0
  },
  "eggGroups": [
    "undiscovered"
  ],
  "drops": {},
  "moves": [
    "1:chargebeam",
    "6:laserfocus",
    "12:flameburst",
    "23:expandingforce",
    "28:mysticalfire",
    "34:simplebeam",
    "39:hex",
    "45:eeriespell",
    "50:fireblast",
    "56:powertrick",
    "61:inferno",
    "72:thunder",
    "78:burnup",
    "83:hyperbeam",
    "tm:zenheadbutt",
    "tm:trick",
    "tm:shockwave",
    "tm:mysticalfire",
    "tm:icywind",
    "tm:drillrun",
    "tm:magiccoat",
    "tm:snore",
    "tm:psychicterrain",
    "tm:powergem",
    "tm:focusenergy",
    "tm:storedpower",
    "tm:weatherball",
    "tm:terrainpulse",
    "tm:meteorbeam",
    "tm:mistyexplosion",
    "tm:psyshock",
    "tm:hiddenpower",
    "tm:sunnyday",
    "tm:taunt",
    "tm:icebeam",
    "tm:blizzard",
    "tm:hyperbeam",
    "tm:lightscreen",
    "tm:protect",
    "tm:solarbeam",
    "tm:thunderbolt",
    "tm:thunder",
    "tm:return",
    "tm:psychic",
    "tm:shadowball",
    "tm:painsplit",
    "tm:reflect",
    "tm:flamethrower",
    "tm:fireblast",
    "tm:facade",
    "tm:flamecharge",
    "tm:rest",
    "tm:luckychant",
    "tm:ancientpower",
    "tm:signalbeam",
    "tm:overheat",
    "tm:energyball",
    "tm:psychocut",
    "tm:chargebeam",
    "tm:curse",
    "tm:willowisp",
    "tm:flash",
    "tm:gigaimpact",
    "tm:thunderwave",
    "tm:grassknot",
    "tm:swagger",
    "tm:sleeptalk",
    "tm:substitute",
    "tm:flashcannon",
    "tm:trickroom",
    "tm:triattack",
    "tm:naturalgift",
    "tm:darkpulse",
    "tm:dazzlinggleam",
    "tm:confide",
    "tm:trailblaze",
    "tm:skillswap",
    "tm:hex",
    "tm:gravity",
    "tm:heatwave",
    "tm:terablast"
  ],
  "labels": [
    "novrai",
    "not_modeled",
    "ultra_beast"
  ],
  "pokedex": [
    "cobblemon.species.magemeltre.desc"
  ],
  "height": 13,
  "weight": 165,
  "aspects": [],
  "evolutions": [],
  "nationalPokedexNumber": 6905,
  "shoulderMountable": false,
  "hitbox": {
    "width": 4.875,
    "height": 4.875,
    "fixed": false
  },
  "features": [],
  "implemented": true,
  "forms": []
}