{
  "species": "cobblemon:snogre",
  "order": 0,
  "variations": [
    {
      "aspects": [],
      "model": "cobblemon:cutout_gravelmon.geo",
      "poser": "cobblemon:sage_snogre",
      "texture": "cobblemon:textures/pokemon/sage/snogre.png",
      "layers": []
    },
    {
      "aspects": [
        "shiny"
      ],
      "texture": "cobblemon:textures/pokemon/sage/snogre_shiny.png"
    },
    {
      "aspects": [
        "female"
      ],
      "texture": "cobblemon:textures/pokemon/sage/snogre_female.png"
    },
    {
      "aspects": [
        "female",
        "shiny"
      ],
      "texture": "cobblemon:textures/pokemon/sage/snogre_female_shiny.png"
    }
  ]
}