{
  "enabled": true,
  "neededInstalledMods": [],
  "neededUninstalledMods": [],
  "spawns": [
    {
      "id": "cefiran_lopunny-01",
      "pokemon": "lopunny cefiran",
      "presets": [
        "natural"
      ],
      "type": "pokemon",
      "context": "grounded",
      "bucket": "common",
      "level": "23-43",
      "weight": 1.2,
      "condition": {
        "biomes": [
          "#cobblemon:is_snowy_forest"
        ],
        "minSkyLight": 8,
        "maxSkyLight": 15
      },
      "weightMultiplier": {
        "multiplier": 5.0,
        "condition": {
          "neededNearbyBlocks": [
            "minecraft:packed_ice"
          ]
        }
      }
    },
    {
      "id": "delta_lopunny-01",
      "pokemon": "lopunny delta",
      "presets": [
        "natural"
      ],
      "type": "pokemon",
      "context": "grounded",
      "bucket": "common",
      "level": "28-48",
      "weight": 0.5,
      "condition": {
        "biomes": [
          "#cobblemon:is_desert"
        ]
      },
      "weightMultiplier": {
        "multiplier": 5.0,
        "condition": {
          "neededNearbyBlocks": [
            "minecraft:target_block"
          ]
        }
      }
    },
    {
      "id": "epoch_lopunny-01",
      "pokemon": "lopunny epoch",
      "presets": [
        "natural"
      ],
      "type": "pokemon",
      "context": "grounded",
      "bucket": "rare",
      "level": "34-54",
      "weight": 0.09,
      "condition": {
        "biomes": [
          "#cobblemon:is_freezing"
        ],
        "timeRange": "night"
      },
      "weightMultiplier": {
        "multiplier": 5.0,
        "condition": {
          "neededNearbyBlocks": [
            "minecraft:purpur"
          ]
        }
      }
    },
    {
      "id": "mikitarian_lopunny-01",
      "pokemon": "lopunny mikitarian",
      "presets": [
        "near_crops"
      ],
      "type": "pokemon",
      "context": "grounded",
      "bucket": "common",
      "level": "27-47",
      "weight": 0.9,
      "condition": {
        "biomes": [
          "#cobblemon:is_taiga",
          "#cobblemon:is_cold"
        ],
        "timeRange": "night"
      },
      "weightMultiplier": {
        "multiplier": 5.0,
        "condition": {
          "neededNearbyBlocks": [
            "minecraft:black_wool"
          ]
        }
      }
    }
  ]
}