{
  "species": "cobblemon:voltorb",
  "order": 3,
  "variations": [
    {
      "aspects": [
        "norheiman"
      ],
      "model": "cobblemon:cutout_gravelmon.geo",
      "poser": "cobblemon:generation1_norheimanvoltorb",
      "texture": "cobblemon:textures/pokemon/generation1/norheimanvoltorb.png",
      "layers": [
        {
          "name": "glow"
        },
        {
          "name": "emissive2"
        },
        {
          "name": "emissive"
        },
        {
          "name": "transparentEmissive"
        },
        {
          "name": "flame"
        },
        {
          "name": "tail"
        }
      ]
    },
    {
      "aspects": [
        "norheiman",
        "shiny"
      ],
      "model": "cobblemon:cutout_gravelmon.geo",
      "poser": "cobblemon:generation1_norheimanvoltorb",
      "texture": "cobblemon:textures/pokemon/generation1/norheimanvoltorb_shiny.png",
      "layers": [
        {
          "name": "glow"
        },
        {
          "name": "emissive2"
        },
        {
          "name": "emissive"
        },
        {
          "name": "transparentEmissive"
        },
        {
          "name": "flame"
        },
        {
          "name": "tail"
        }
      ]
    }
  ]
}