{
  "species": "cobblemon:ivysaur",
  "order": 133,
  "variations": [
    {
      "aspects": [
        "delta"
      ],
      "model": "cobblemon:insurgence_deltaivysaur.geo",
      "poser": "cobblemon:insurgence_deltaivysaur",
      "texture": "cobblemon:textures/pokemon/insurgence/deltaivysaur/deltaivysaur.png",
      "layers": [
        {
          "name": "emissive"
        },
        {
          "name": "transparentEmissive"
        },
        {
          "name": "tail"
        },
        {
          "name": "transparent_emissive"
        },
        {
          "name": "emissive2"
        },
        {
          "name": "flame"
        },
        {
          "name": "glow"
        },
        {
          "texture": "cobblemon:textures/empty_texture.png"
        }
      ]
    },
    {
      "aspects": [
        "delta",
        "shiny"
      ],
      "model": "cobblemon:insurgence_deltaivysaur.geo",
      "poser": "cobblemon:insurgence_deltaivysaur",
      "texture": "cobblemon:textures/pokemon/insurgence/deltaivysaur/deltaivysaur_shiny.png",
      "layers": [
        {
          "name": "emissive"
        },
        {
          "name": "transparentEmissive"
        },
        {
          "name": "tail"
        },
        {
          "name": "transparent_emissive"
        },
        {
          "name": "emissive2"
        },
        {
          "name": "flame"
        },
        {
          "name": "glow"
        },
        {
          "texture": "cobblemon:textures/empty_texture.png"
        }
      ]
    },
    {
      "aspects": [
        "delta",
        "female"
      ],
      "model": "cobblemon:insurgence_deltaivysaur.geo",
      "poser": "cobblemon:insurgence_deltaivysaur",
      "texture": "cobblemon:textures/pokemon/insurgence/deltaivysaur/deltaivysaur_female.png",
      "layers": [
        {
          "name": "emissive"
        },
        {
          "name": "transparentEmissive"
        },
        {
          "name": "tail"
        },
        {
          "name": "transparent_emissive"
        },
        {
          "name": "emissive2"
        },
        {
          "name": "flame"
        },
        {
          "name": "glow"
        },
        {
          "texture": "cobblemon:textures/empty_texture.png"
        }
      ]
    },
    {
      "aspects": [
        "delta",
        "female",
        "shiny"
      ],
      "model": "cobblemon:insurgence_deltaivysaur.geo",
      "poser": "cobblemon:insurgence_deltaivysaur",
      "texture": "cobblemon:textures/pokemon/insurgence/deltaivysaur/deltaivysaur_female_shiny.png",
      "layers": [
        {
          "name": "emissive"
        },
        {
          "name": "transparentEmissive"
        },
        {
          "name": "tail"
        },
        {
          "name": "transparent_emissive"
        },
        {
          "name": "emissive2"
        },
        {
          "name": "flame"
        },
        {
          "name": "glow"
        },
        {
          "texture": "cobblemon:textures/empty_texture.png"
        }
      ]
    }
  ]
}