{
  "species": "cobblemon:tinkatink",
  "order": 140,
  "variations": [
    {
      "aspects": [
        "lagoonan"
      ],
      "model": "cobblemon:cutout_gravelmon_44_by_43.geo",
      "poser": "cobblemon:cutout_gravelmon_44_by_43",
      "texture": "cobblemon:textures/pokemon/generation9/lagoonantinkatink.png",
      "layers": [
        {
          "name": "emissive"
        },
        {
          "name": "transparentEmissive"
        },
        {
          "name": "tail"
        },
        {
          "name": "transparent_emissive"
        },
        {
          "name": "emissive2"
        },
        {
          "name": "flame"
        },
        {
          "name": "glow"
        }
      ]
    }
  ]
}