{
  "species": "cobblemon:milcery",
  "order": 3,
  "variations": [
    {
      "aspects": [
        "varitasian"
      ],
      "model": "cobblemon:cutout_gravelmon.geo",
      "poser": "cobblemon:generation8_varitasianmilcery",
      "texture": "cobblemon:textures/pokemon/generation8/varitasianmilcery.png",
      "layers": [
        {
          "name": "glow"
        },
        {
          "name": "emissive2"
        },
        {
          "name": "emissive"
        },
        {
          "name": "transparentEmissive"
        },
        {
          "name": "flame"
        },
        {
          "name": "tail"
        }
      ]
    },
    {
      "aspects": [
        "varitasian",
        "shiny"
      ],
      "model": "cobblemon:cutout_gravelmon.geo",
      "poser": "cobblemon:generation8_varitasianmilcery",
      "texture": "cobblemon:textures/pokemon/generation8/varitasianmilcery.png",
      "layers": [
        {
          "name": "glow"
        },
        {
          "name": "emissive2"
        },
        {
          "name": "emissive"
        },
        {
          "name": "transparentEmissive"
        },
        {
          "name": "flame"
        },
        {
          "name": "tail"
        }
      ]
    }
  ]
}