{
  "implemented": true,
  "name": "bonzire",
  "nationalPokedexNumber": 3015,
  "primaryType": "fire",
  "secondaryType": "electric",
  "abilities": [
    "flashfire",
    "voltabsorb",
    "h:motordrive"
  ],
  "baseStats": {
    "hp": 75,
    "attack": 75,
    "defence": 60,
    "special_attack": 100,
    "special_defence": 60,
    "speed": 90
  },
  "behaviour": {
    "resting": {
        "canSleep": true,
        "willSleepOnBed": false,        "depth": "normal",
        "light": "0-6"
    },
    "moving": {
        "fly": {
            "canFly": false
        },
        "canLook": true,
        "walk": {
            "canWalk": true,
            "avoidsLand": false
        },
        "swim": {
            "swimSpeed": 0.1,
            "canSwimInWater": true,
            "canBreatheUnderwater": false
        }
    }
  },
  "catchRate": 75,
  "maleRatio": 0.5,
  "shoulderMountable": false,
  "baseExperienceYield": 113,
  "experienceGroup": "medium_fast",
  "eggCycles": 50,
  "eggGroups": [
    "field",
    "fairy"
  ],
  "moves": [
    "1:incinerate",
    "41:fireblast",
    "46:electroball",
    "53:thunder",
    "tm:heatwave",
    "tm:helpinghand",
    "tm:tickle",
    "tm:covet",
    "tm:disarmingvoice"  ],
  "labels": [
    "orohnhavai",
    "not_modeled",
    "fakemon",
    "fakemonevolution"
  ],
  "pokedex": [
    "cobblemon.species.bonzire.desc"
  ],
  "preEvolution": "bonzumi",
  "baseScale": 0.16666666666666666,
  "hitbox": {
    "width": 6.0,
    "height": 6.0,
    "fixed": false
  },
  "baseFriendship": 70,
  "evYield": {
    "hp": 0,
    "attack": 0,
    "defence": 0,
    "special_attack": 2,
    "special_defence": 0,
    "speed": 0
  },
  "height": 10,
  "weight": 165,
  "aspects": [],
"features": [

  ],  "cannotDynamax": false
}